pet_bit_melody/__init__.py
pet_bit_melody/__main__.py
pet_bit_melody/main.py
tests/__init__.py
tests/test_pet_bit_melody.py
pet_bit_melody-0.0.1.dist-info/LICENSE
pet_bit_melody-0.0.1.dist-info/METADATA
pet_bit_melody-0.0.1.dist-info/WHEEL
pet_bit_melody-0.0.1.dist-info/top_level.txt
pet_bit_melody-0.0.1.dist-info/RECORD
