Metadata-Version: 2.1
Name: pet_bit_melody
Version: 0.0.1
Summary: This is a music player/composer for 8, 16, 32 bit and piano cord music.
Home-page: https://github.com/Hanra-s-work/pet_bit_melody
Author: Henry Letellier
Author-email: henrysoftwarehouse@protonmail.com
Classifier: Programming Language :: Python :: 3
Classifier: License :: OSI Approved :: MIT License
Classifier: Operating System :: OS Independent
License-File: LICENSE
